{
    "configurations": [
        {
            "name": "AVR (ATMega1284P)",
            "includePath": [
                "${workspaceFolder}/build/autogen/superkey",
                "${workspaceFolder}/src/main"
            ],
            "defines": [
                "MCU=\"atmega1284p\"",
                "F_CPU=16000000",
                "_DEBUG=1",
                "_BUILD_TYPE=\"Debug\"",
                "_FEATURE_ON=1",
                "_FEATURE_OFF=0",
                "_FEATURE_ENABLE_DEBUG_PORT=_FEATURE_ON",
                "_FEATURE_OPT_DEBUG_PORT_BAUD=USART_BAUD_38400",
                "_CONFIG_DFLT_WPM=200",
                "_CONFIG_DFLT_WPM_ELEMENT_SCALE=1.0f",
                "_CONFIG_DFLT_BUZZER_ENABLED=true",
                "_CONFIG_DFLT_BUZZER_FREQUENCY=700",
                "_CONFIG_DFLT_LED_STATUS_ENABLED=true",
                "_CONFIG_DFLT_LED_KEY_ENABLED=true",
                "_CONFIG_DFLT_IO_TYPE_TRS_0_TIP=IO_TYPE_INPUT_STRAIGHT_KEY",
                "_CONFIG_DFLT_IO_POLARITY_TRS_0_TIP=IO_POLARITY_ACTIVE_LOW",
                "_CONFIG_DFLT_IO_TYPE_TRS_0_RING=IO_TYPE_NONE",
                "_CONFIG_DFLT_IO_POLARITY_TRS_0_RING=IO_POLARITY_ACTIVE_LOW",
                "_CONFIG_DFLT_IO_TYPE_TRS_1_TIP=IO_TYPE_INPUT_PADDLE_LEFT",
                "_CONFIG_DFLT_IO_POLARITY_TRS_1_TIP=IO_POLARITY_ACTIVE_LOW",
                "_CONFIG_DFLT_IO_TYPE_TRS_1_RING=IO_TYPE_INPUT_PADDLE_RIGHT",
                "_CONFIG_DFLT_IO_POLARITY_TRS_1_RING=IO_POLARITY_ACTIVE_LOW",
                "_CONFIG_DFLT_IO_TYPE_TRS_2_TIP=IO_TYPE_NONE",
                "_CONFIG_DFLT_IO_POLARITY_TRS_2_TIP=IO_POLARITY_ACTIVE_LOW",
                "_CONFIG_DFLT_IO_TYPE_TRS_2_RING=IO_TYPE_NONE",
                "_CONFIG_DFLT_IO_POLARITY_TRS_2_RING=IO_POLARITY_ACTIVE_LOW",
                "_CONFIG_DFLT_IO_TYPE_TRS_3_TIP=IO_TYPE_OUTPUT_KEYER",
                "_CONFIG_DFLT_IO_POLARITY_TRS_3_TIP=IO_POLARITY_ACTIVE_LOW",
                "_CONFIG_DFLT_IO_TYPE_TRS_3_RING=IO_TYPE_NONE",
                "_CONFIG_DFLT_IO_POLARITY_TRS_3_RING=IO_POLARITY_ACTIVE_LOW",
                "_CONFIG_DFLT_KEYER_PADDLE_MODE=KEYER_PADDLE_MODE_IAMBIC",
                "_CONFIG_DFLT_KEYER_PADDLE_INVERT=false"
            ],
            "compilerPath": "/usr/bin/avr-gcc",
            "compilerArgs": [
                "-mmcu=atmega1284p",
                "-Wall",
                "-Wextra",
                "-Wpedantic",
                "-Os",
                "-g"
            ],
            "cStandard": "c11",
            "cppStandard": "gnu++14",
            "intelliSenseMode": "linux-gcc-x64"
        }
    ],
    "version": 4
}
